{
    "ADP": [
        "без",
        "безо",
        "благодаря",
        "близ",
        "в",
        "вблизи",
        "ввиду",
        "вглубь",
        "вдоль",
        "взамен",
        "включая",
        "вкруг",
        "вместо",
        "вне",
        "внизу",
        "внутри",
        "внутрь",
        "во",
        "возле",
        "вокруг",
        "вопреки",
        "впереди",
        "вроде",
        "вслед",
        "вследствие",
        "для",
        "до",
        "за",
        "заместо",
        "из",
        "из-за",
        "из-под",
        "изнутри",
        "изо",
        "к",
        "касательно",
        "ко",
        "кроме",
        "меж",
        "между",
        "мимо",
        "на",
        "навроде",
        "навстречу",
        "над",
        "надо",
        "назад",
        "накануне",
        "наподобие",
        "напротив",
        "насчёт",
        "о",
        "об",
        "обо",
        "около",
        "от",
        "относительно",
        "ото",
        "параллельно",
        "перед",
        "передо",
        "по",
        "по-над",
        "поверх",
        "под",
        "подле",
        "подо",
        "подобно",
        "позади",
        "помимо",
        "поперёк",
        "порядка",
        "посередине",
        "после",
        "посреди",
        "посредине",
        "превыше",
        "пред",
        "предо",
        "прежде",
        "при",
        "про",
        "против",
        "ради",
        "с",
        "сверх",
        "свыше",
        "сквозь",
        "снаружи",
        "со",
        "согласно",
        "сообразно",
        "соответственно",
        "соразмерно",
        "спустя",
        "среди",
        "средь",
        "супротив",
        "типа",
        "у",
        "через",
        "чрез"
    ],
    "CONJ" : [
        "а",
        "аки",
        "благо",
        "буде",
        "будто",
        "ведь",
        "да",
        "дабы",
        "едва",
        "ежели",
        "если",
        "зато",
        "и",
        "и/или",
        "ибо",
        "или",
        "иначе",
        "кабы",
        "как",
        "когда",
        "коли",
        "коль",
        "либо",
        "лишь",
        "минус",
        "насколько",
        "нежели",
        "ни",
        "но",
        "однако",
        "отсюда",
        "плюс",
        "пока",
        "покамест",
        "покуда",
        "поскольку",
        "пускай",
        "пусть",
        "раз",
        "с",
        "сколько",
        "словно",
        "со",
        "т.к.",
        "так",
        "тем",
        "то",
        "тогда",
        "только",
        "тот",
        "точно",
        "хоть",
        "хотя",
        "чем",
        "что",
        "чтоб",
        "чтобы",
        "чуть"
    ],
    "DET" : [
        "ваш",
        "весь",
        "всякий",
        "всяк",
        "другой",
        "его",
        "её",
        "иной",
        "ихний",
        "их",
        "каждый",
        "каков",
        "какой",
        "какой-либо",
        "какой-нибудь",
        "какой-то",
        "кой",
        "который",
        "который-нибудь",
        "любой",
        "многие",
        "мой",
        "наш",
        "некий",
        "некоторый",
        "немногие",
        "никакой",
        "ничей",
        "оный",
        "прочий",
        "проч.",
        "пр.",
        "свой",
        "сей",
        "таков",
        "такой",
        "твой",
        "тот",
        "чей",
        "чей-либо",
        "чей-нибудь",
        "чей-то",
        "этакий",
        "этот",
        "некто"
    ],
    "H": [
        "бывает",
        "бывало",
        "вестимо",
        "видать",
        "впрочем",
        "выходит",
        "значит",
        "имхо",
        "кажись",
        "короче",
        "кроме",
        "может",
        "наверно",
        "наверное",
        "однако",
        "поди",
        "пожалуй",
        "почитай",
        "правда",
        "право",
        "притом",
        "разумеется",
        "следовательно",
        "так",
        "в",
        "к",
        "тем",
        "что"
    ],
    "PART": [
        "Вот",
        "Ли",
        "Электро—это",
        "абы",
        "аж",
        "б",
        "бишь",
        "будто",
        "бы",
        "было",
        "ведь",
        "вон",
        "вот",
        "вроде",
        "всего",
        "всех",
        "да",
        "даже",
        "дескать",
        "ж",
        "же",
        "за",
        "и",
        "именно",
        "ка",
        "как",
        "как-то",
        "кое",
        "ладно",
        "ли",
        "лишь",
        "ль",
        "мало",
        "много",
        "мол",
        "также",
        "нате",
        "не",
        "незнамо",
        "неизвестно",
        "нет",
        "неужели",
        "неужто",
        "нешто",
        "ни",
        "ну",
        "плиз",
        "пожалуйста",
        "пока",
        "попало",
        "прямо",
        "разве",
        "конечно",
        "редко",
        "ровно",
        "словно",
        "так",
        "таки",
        "там",
        "типа",
        "то",
        "только",
        "угодно",
        "уж",
        "ужели",
        "ужель",
        "хорошо",
        "хоть",
        "что",
        "это",
        "якобы",
        "все"
    ],
    "PRON": [
        "все",
        "вы",
        "кое-кто",
        "кое-что",
        "кто",
        "кто-либо",
        "кто-нибудь",
        "кто-то",
        "мы",
        "некого",
        "некто",
        "нечего",
        "нечто",
        "никто",
        "ничто",
        "он",
        "она",
        "это",
        "они",
        "оно",
        "себя",
        "то",
        "тот",
        "ты",
        "что",
        "что-либо",
        "что-нибудь",
        "что-то",
        "я"
    ],
    "FAKE_ADJ": [
        "надо",
        "вольно",
        "можно",
        "возможно"
    ]
}
